[
  {
    "id": 1,
    "name_th": "ราศีเมษ",
    "name_en": "Aries",
    "start_date": "04-13",
    "end_date": "05-14",
    "ruling_planet": "ดาวอังคาร",
    "element": "ไฟ",
    "traits": "กล้าหาญ พลังงานล้นเหลือ เป็นนักบุกเบิก ตรงไปตรงมา",
    "lucky_colors": [
      "แดง",
      "ชมพู"
    ]
  },
  {
    "id": 2,
    "name_th": "ราศีพฤษภ",
    "name_en": "Taurus",
    "start_date": "05-15",
    "end_date": "06-14",
    "ruling_planet": "ดาวศุกร์",
    "element": "ดิน",
    "traits": "รักสงบ ชอบศิลปะและความสุนทรีย์ อดทน มั่นคง",
    "lucky_colors": [
      "ขาว",
      "ครีม",
      "ฟ้า"
    ]
  },
  {
    "id": 3,
    "name_th": "ราศีมิถุน",
    "name_en": "Gemini",
    "start_date": "06-15",
    "end_date": "07-14",
    "ruling_planet": "ดาวพุธ",
    "element": "ลม",
    "traits": "สื่อสารเก่ง ไหวพริบดี เรียนรู้ไว ปรับตัวเข้ากับสถานการณ์ได้เร็ว",
    "lucky_colors": [
      "เขียว",
      "เหลือง"
    ]
  },
  {
    "id": 4,
    "name_th": "ราศีกรกฎ",
    "name_en": "Cancer",
    "start_date": "07-15",
    "end_date": "08-15",
    "ruling_planet": "ดาวจันทร์",
    "element": "น้ำ",
    "traits": "อ่อนโยน มีเมตตา อารมณ์ละเอียดอ่อน ให้ความสำคัญกับครอบครัว",
    "lucky_colors": [
      "ขาว",
      "เงิน",
      "เหลืองอ่อน"
    ]
  },
  {
    "id": 5,
    "name_th": "ราศีสิงห์",
    "name_en": "Leo",
    "start_date": "08-16",
    "end_date": "09-16",
    "ruling_planet": "ดาวอาทิตย์",
    "element": "ไฟ",
    "traits": "มีความเป็นผู้นำสูง โดดเด่น สง่างาม รักศักดิ์ศรี ใจกว้าง",
    "lucky_colors": [
      "ส้ม",
      "แดง",
      "ทอง"
    ]
  },
  {
    "id": 6,
    "name_th": "ราศีกันย์",
    "name_en": "Virgo",
    "start_date": "09-17",
    "end_date": "10-16",
    "ruling_planet": "ดาวพุธ",
    "element": "ดิน",
    "traits": "เจ้าระเบียบ วิเคราะห์เก่ง ทำงานละเอียดรอบคอบ รักความสมบูรณ์แบบ",
    "lucky_colors": [
      "เขียว",
      "เทา",
      "น้ำตาล"
    ]
  },
  {
    "id": 7,
    "name_th": "ราศีตุลย์",
    "name_en": "Libra",
    "start_date": "10-17",
    "end_date": "11-15",
    "ruling_planet": "ดาวศุกร์",
    "element": "ลม",
    "traits": "รักความยุติธรรม มีเสน่ห์ทางสังคม ประนีประนอมเก่ง มีมนุษยสัมพันธ์ดี",
    "lucky_colors": [
      "ฟ้า",
      "น้ำเงิน",
      "ชมพู"
    ]
  },
  {
    "id": 8,
    "name_th": "ราศีพิจิก",
    "name_en": "Scorpio",
    "start_date": "11-16",
    "end_date": "12-15",
    "ruling_planet": "ดาวอังคาร",
    "element": "น้ำ",
    "traits": "ลึกลับ เด็ดขาด มีความมุ่งมั่นและพลังใจสูง อ่านใจคนเก่ง",
    "lucky_colors": [
      "แดงเข้ม",
      "ดำ",
      "น้ำตาลแดง"
    ]
  },
  {
    "id": 9,
    "name_th": "ราศีธนู",
    "name_en": "Sagittarius",
    "start_date": "12-16",
    "end_date": "01-14",
    "ruling_planet": "ดาวพฤหัสบดี",
    "element": "ไฟ",
    "traits": "มองการณ์ไกล รักอิสระ มีปัญญา ชอบเรียนรู้และผจญภัย",
    "lucky_colors": [
      "เหลือง",
      "ส้ม",
      "แดง"
    ]
  },
  {
    "id": 10,
    "name_th": "ราศีมังกร",
    "name_en": "Capricorn",
    "start_date": "01-15",
    "end_date": "02-12",
    "ruling_planet": "ดาวเสาร์",
    "element": "ดิน",
    "traits": "จริงจัง ทะเยอทะยาน อดทนต่อความยากลำบากเก่ง มีความรับผิดชอบสูง",
    "lucky_colors": [
      "ดำ",
      "เทาเข้ม",
      "ม่วง"
    ]
  },
  {
    "id": 11,
    "name_th": "ราศีกุมภ์",
    "name_en": "Aquarius",
    "start_date": "02-13",
    "end_date": "03-14",
    "ruling_planet": "พระราหู",
    "element": "ลม",
    "traits": "มีความคิดแหวกแนว ทันสมัย รักพวกพ้อง ไม่ชอบอยู่ในกรอบ",
    "lucky_colors": [
      "เทา",
      "ดำ",
      "บรอนซ์",
      "ม่วงอ่อน"
    ]
  },
  {
    "id": 12,
    "name_th": "ราศีมีน",
    "name_en": "Pisces",
    "start_date": "03-15",
    "end_date": "04-12",
    "ruling_planet": "ดาวพฤหัสบดี",
    "element": "น้ำ",
    "traits": "จินตนาการสูง เสียสละ มีสัมผัสที่หก เห็นอกเห็นใจผู้อื่น",
    "lucky_colors": [
      "เหลือง",
      "ส้ม",
      "ทอง"
    ]
  }
]